{
    "LongDelay": 300,
    "ShortDelay": 5,
    "SharedSettings": [
        {
            "Key": "ARKStatsExtractorPath",
            "Value": "C:\\Software\\ARKStatsExtractor-Debug\\Debug\\ARK Smart Breeding.exe"
        },
        {
            "Key": "ARKStatsExtractorTimeout",
            "Value": 30
        }
    ],
    "MonitoringSources": [
        { "ExternalConfiguration": "ArkConfig-TheIsland.json" },
        { "ExternalConfiguration": "ArkConfig-Scorched.json" },
        { "ExternalConfiguration": "ArkConfig-Aberration.json" },
        { "ExternalConfiguration": "ArkConfig-Extinction.json" },
        { "ExternalConfiguration": "ArkConfig-Ragnarok.json" },
        { "ExternalConfiguration": "ArkConfig-Genesis1.json" },
        { "ExternalConfiguration": "ArkConfig-Fjordur.json" },
        { "ExternalConfiguration": "ArkConfig-Genesis2.json" },
        { "ExternalConfiguration": "ArkConfig-TheCenter.json" }
    ]
}
